project_init/__init__.py
project_init/main.py
project_init/requirements.txt
project_init/styles/__init__.py
project_init/styles/colors.py
project_init/templates/__init__.py
project_init/templates/aiogram.py
project_init/templates/pyqt.py
project_init/utils/__init__.py
project_init/utils/env.py
project_init/utils/structure.py
create_base_projects-0.1.0.dist-info/entry_points.txt
create_base_projects-0.1.0.dist-info/METADATA
create_base_projects-0.1.0.dist-info/WHEEL
create_base_projects-0.1.0.dist-info/RECORD
