Metadata-Version: 2.3
Name: create-base-projects
Version: 0.1.0
Summary: This library I created just for self use, if you want you can use it too
Author: Арсений
Author-email: workmailskr@mail.ru
Requires-Python: >=3.12,<4.0
Classifier: Programming Language :: Python :: 3
Classifier: Programming Language :: Python :: 3.12
Classifier: Programming Language :: Python :: 3.13
Requires-Dist: inquirer (==3.4.0)
Requires-Dist: inquirerpy (==0.3.4)
Requires-Dist: typer (>=0.15.1,<0.16.0)
